<?xml version="1.0" encoding="utf-8" ?><dwsync><file name="analytics.js" server="94.23.18.157/sd/newtech/www/" local="3430116694" remote="319519907829056980" Dst="-1" /><file name="calendar-android.js" server="94.23.18.157/sd/newtech/www/" local="3431409880" remote="319519907829056980" Dst="-1" /><file name="Camera.js" server="94.23.18.157/sd/newtech/www/" local="3432183794" remote="319519907829056980" Dst="-1" /><file name="ChildBrowser-android.js" server="94.23.18.157/sd/newtech/www/" local="3431409902" remote="319519907829056980" Dst="-1" /><file name="deviceinfo-android.js" server="94.23.18.157/sd/newtech/www/" local="3434449933" remote="319519907829056980" Dst="-1" /><file name="OrientationHandler.js" server="94.23.18.157/sd/newtech/www/" local="3432189562" remote="319519907829056980" Dst="-1" /><file name="sns-android.js" server="94.23.18.157/sd/newtech/www/" local="3436509319" remote="319519907830179760" Dst="-1" /><file name="cordova-2.2.0.js" server="94.23.18.157/sd/newtech/www/" local="3434615014" remote="319519907829057040" Dst="-1" /></dwsync>